setup.py
Essential_Probability_Functions/Binomialdistribution.py
Essential_Probability_Functions/Gaussiandistribution.py
Essential_Probability_Functions/Generaldistribution.py
Essential_Probability_Functions/__init__.py
Essential_Probability_Functions.egg-info/PKG-INFO
Essential_Probability_Functions.egg-info/SOURCES.txt
Essential_Probability_Functions.egg-info/dependency_links.txt
Essential_Probability_Functions.egg-info/not-zip-safe
Essential_Probability_Functions.egg-info/top_level.txt