Metadata-Version: 1.0
Name: Essential-Probability-Functions
Version: 0.1
Summary: Gaussian distributions and Binomial distributions
Home-page: UNKNOWN
Author: Muhammed Essam
Author-email: muhammed.essam00@gmail.com
License: UNKNOWN
Platform: UNKNOWN
